nested_diff_restful/__init__.py
nested_diff_restful/api.py
nested_diff_restful/static/favicon.svg
nested_diff_restful/static/nested_diff.js
nested_diff_restful/templates/index.html
nested_diff_restful-1.1.0.dist-info/entry_points.txt
nested_diff_restful-1.1.0.dist-info/LICENSE
nested_diff_restful-1.1.0.dist-info/WHEEL
nested_diff_restful-1.1.0.dist-info/METADATA
nested_diff_restful-1.1.0.dist-info/RECORD
