Metadata-Version: 2.1
Name: nested_diff_restful
Version: 1.1.0
Summary: REST API and web UI for nested-diff
Keywords: api,diff,nested-diff,recursive-diff,rest
Author-email: Michael Samoglyadov <mixas.sr@gmail.com>
Requires-Python: >=3.8
Classifier: Development Status :: 4 - Beta
Classifier: Intended Audience :: Developers
Classifier: Intended Audience :: Information Technology
Classifier: Intended Audience :: System Administrators
Classifier: License :: OSI Approved :: Apache Software License
Classifier: Operating System :: OS Independent
Classifier: Programming Language :: Python :: 3 :: Only
Classifier: Programming Language :: Python :: 3.8
Classifier: Programming Language :: Python :: 3.9
Classifier: Programming Language :: Python :: 3.10
Classifier: Programming Language :: Python :: 3.11
Classifier: Programming Language :: Python :: 3.12
Requires-Dist: flask
Requires-Dist: gunicorn
Requires-Dist: nested_diff>=1.3.2
Requires-Dist: pytest ; extra == "test"
Requires-Dist: pytest-cov ; extra == "test"
Requires-Dist: pytest-ruff ; extra == "test"
Requires-Dist: ruff==0.1.15 ; extra == "test"
Project-URL: Homepage, https://github.com/mr-mixas/Nested-Diff-RESTful
Project-URL: Repository, https://github.com/mr-mixas/Nested-Diff-RESTful.git
Provides-Extra: test
